hippogriffe/__init__.py
hippogriffe/_extension.py
hippogriffe/_plugin.py
hippogriffe/assets/_hippogriffe.css
hippogriffe/templates/material/hippogriffe/class.html.jinja
hippogriffe/templates/material/hippogriffe/fn.html.jinja
hippogriffe/templates/material/hippogriffe/hippogriffe.jinja
hippogriffe-0.2.2.dist-info/METADATA
hippogriffe-0.2.2.dist-info/WHEEL
hippogriffe-0.2.2.dist-info/entry_points.txt
hippogriffe-0.2.2.dist-info/licenses/LICENSE
hippogriffe-0.2.2.dist-info/RECORD
