Metadata-Version: 2.4
Name: hippogriffe
Version: 0.2.2
Summary: Tweaks for `mkdocstrings[python]`
Project-URL: repository, https://github.com/patrick-kidger/hippogriffe
Author-email: Patrick Kidger <contact@kidger.site>
License:                                  Apache License
License-File: LICENSE
Keywords: griffe,markdown,md,mkdocs,mkdocstrings
Classifier: Development Status :: 3 - Alpha
Classifier: License :: OSI Approved :: Apache Software License
Classifier: Natural Language :: English
Classifier: Programming Language :: Python :: 3
Requires-Python: >=3.10
Requires-Dist: griffe>=1.6.0
Requires-Dist: mkdocs>=1.6.1
Requires-Dist: mkdocstrings[python]>=0.28.3
Requires-Dist: wadler-lindig>=0.1.4
Provides-Extra: dev
Requires-Dist: pre-commit; extra == 'dev'
